{
  "_meta": {
    "observer": "铸渊全链路部署观测系统 v1.0",
    "copyright": "国作登字-2026-A-00037559",
    "collected_at": "2026-04-12T08:24:08.222Z"
  },
  "run": {
    "id": 24302362370,
    "workflow_name": "🏛️ 铸渊主权服务器 · 部署",
    "conclusion": "success",
    "status": "completed",
    "html_url": "https://github.com/qinfendebingshuo/guanghulab/actions/runs/24302362370",
    "head_sha": "cbd4f32bf38db00d8a9469153dbc1a1bee694185",
    "head_branch": "main",
    "actor": "qinfendebingshuo",
    "created_at": "2026-04-12T08:22:31Z",
    "updated_at": "2026-04-12T08:23:55Z",
    "run_started_at": "2026-04-12T08:22:31Z"
  },
  "jobs_summary": {
    "total": 5,
    "success": 1,
    "failure": 0,
    "skipped": 4,
    "cancelled": 0
  },
  "failed_jobs": [],
  "all_jobs": [
    {
      "id": 70957814922,
      "name": "🚀 部署应用代码",
      "status": "completed",
      "conclusion": "success",
      "started_at": "2026-04-12T08:22:36Z",
      "completed_at": "2026-04-12T08:23:54Z"
    },
    {
      "id": 70957814969,
      "name": "💚 健康检查",
      "status": "completed",
      "conclusion": "skipped",
      "started_at": "2026-04-12T08:22:32Z",
      "completed_at": "2026-04-12T08:22:32Z"
    },
    {
      "id": 70957815080,
      "name": "🔒 SSL证书配置",
      "status": "completed",
      "conclusion": "skipped",
      "started_at": "2026-04-12T08:22:32Z",
      "completed_at": "2026-04-12T08:22:32Z"
    },
    {
      "id": 70957815102,
      "name": "🔧 服务器初始化",
      "status": "completed",
      "conclusion": "skipped",
      "started_at": "2026-04-12T08:22:32Z",
      "completed_at": "2026-04-12T08:22:32Z"
    },
    {
      "id": 70957815145,
      "name": "🚀 预览站→主站 一键推送",
      "status": "completed",
      "conclusion": "skipped",
      "started_at": "2026-04-12T08:22:32Z",
      "completed_at": "2026-04-12T08:22:32Z"
    }
  ],
  "analysis": {
    "needs_repair": false,
    "error_summary": "",
    "matched_patterns": [],
    "recommendation": ""
  }
}
